{
  "lastUpdated": "2025-08-16T00:00:10.055Z",
  "stats": {
    "users": {
      "count": 77848,
      "change": 14.1
    },
    "revenue": {
      "amount": 309112,
      "change": -0.1
    },
    "projects": {
      "count": 376,
      "change": 2.5
    },
    "tasks": {
      "count": 2747,
      "change": 2.2
    }
  },
  "activities": [
    {
      "type": "user",
      "title": "Task completed",
      "timestamp": "2025-08-16T00:00:10.055Z"
    },
    {
      "type": "alert",
      "title": "User updated profile",
      "timestamp": "2025-08-15T00:01:03.986Z"
    },
    {
      "type": "task",
      "title": "Task completed",
      "timestamp": "2025-08-14T00:00:27.983Z"
    },
    {
      "type": "user",
      "title": "Task completed",
      "timestamp": "2025-08-13T00:00:42.671Z"
    },
    {
      "type": "task",
      "title": "Task assigned",
      "timestamp": "2025-08-12T00:00:28.913Z"
    }
  ],
  "weeklyActivity": [
    {
      "day": "Mon",
      "value": 16
    },
    {
      "day": "Tue",
      "value": 17
    },
    {
      "day": "Wed",
      "value": 78
    },
    {
      "day": "Thu",
      "value": 11
    },
    {
      "day": "Fri",
      "value": 20
    },
    {
      "day": "Sat",
      "value": 15
    },
    {
      "day": "Sun",
      "value": 51
    }
  ],
  "performanceMetrics": [
    {
      "date": "2023-11-06",
      "value": 30
    },
    {
      "date": "2023-11-07",
      "value": 45
    },
    {
      "date": "2023-11-08",
      "value": 17
    },
    {
      "date": "2023-11-09",
      "value": 29
    },
    {
      "date": "2023-11-10",
      "value": 29
    },
    {
      "date": "2023-11-11",
      "value": 19
    },
    {
      "date": "2023-11-12",
      "value": 41
    }
  ]
}